aie_secrets
