Metadata-Version: 2.1
Name: aie-secrets
Version: 20.0.0
Summary: My first Python package
Author: johnson
Author-email: johnssimon007@email.com
License-File: LICENSE
